setup.py
pydiffparser/__init__.py
pydiffparser/model.py
pydiffparser/parsing.py
pydiffparser.egg-info/PKG-INFO
pydiffparser.egg-info/SOURCES.txt
pydiffparser.egg-info/dependency_links.txt
pydiffparser.egg-info/requires.txt
pydiffparser.egg-info/top_level.txt