Metadata-Version: 1.1
Name: pydiffparser
Version: 0.1
Summary: Diff files parser for Python
Home-page: https://github.com/ftomassetti/pydiffparser
Author: Federico Tomassetti
Author-email: Federico Tomassetti
License: UNKNOWN
Platform: UNKNOWN
Classifier: Programming Language :: Python
Classifier: License :: OSI Approved :: MIT License
Classifier: Operating System :: OS Independent
Classifier: Development Status :: 3 - Alpha
